{
  "name": "geologic_surfaces",
  "display": "ϱèôℓôϱïç_ƨúřƒáçèƨ",
  "desc": "Tλè ϱèôℓôϱïç_ƨúřƒáçèƨ ₥ôδúℓè ƥřôƲïδèƨ çô₥ƥℓèƭè çôñƭřôℓ ôƒ δïƨƥℓá¥ïñϱ, ƨçáℓïñϱ áñδ èжƥℓôδïñϱ ôñè ôř ₥ôřè ϱèôℓôϱïç ƨúřƒáçèƨ ƒřô₥ á ƨèƭ ôƒ ƨúřƒáçèƨ.",
  "categories": [
    {
      "name": "Properties",
      "display": "Þřôƥèřƭïèƨ",
      "properties": []
    },
    {
      "name": "Surface Settings",
      "display": "§úřƒáçè §èƭƭïñϱƨ",
      "properties": [
        {
          "name": "Surface Offset",
          "display": "§úřƒáçè Óƒƒƨèƭ",
          "desc": "Tλè §úřƒáçè Z Óƒƒƨèƭ ƥářá₥èƭèř ƨƥèçïƒïèƨ ƭλè δïƨƭáñçè ƭλáƭ ƭλè ƨúřƒáçè ωïℓℓ βè ƭřáñƨℓáƭèδ ïñ ƭλè Z áжïƨ βèƒôřè δïƨƥℓá¥."
        },
        {
          "name": "Minimum Thickness",
          "display": "Mïñï₥ú₥ Tλïçƙñèƨƨ",
          "desc": "Tλè Mïñï₥ú₥ Tλïçƙñèƨƨ ƥářá₥èƭèř δèƭèř₥ïñèƨ ƭλè ₥ïñï₥ú₥ ƨƥáçïñϱ βèƭωèèñ ƨúřƒáçèƨ ωλèñ λïèřářçλ¥ ïƨ ï₥ƥôƨèδ."
        },
        {
          "name": "Account For Hierarchy",
          "display": "Âççôúñƭ Fôř Hïèřářçλ¥",
          "desc": "Tλè Âççôúñƭ ƒôř Hïèřářçλ¥ ƭôϱϱℓè çáúƨèƨ ϱèôℓôϱïç ƨúřƒáçèƨ ƭλáƭ ₥ïϱλƭ ôƭλèřωïƨè ïñƭèřƨèçƭ èáçλ ôƭλèř ƭô βè çôřřèçƭèδ ƭô áççôúñƭ ƒôř Gèôℓôϱïç Hïèřářçλ¥."
        },
        {
          "name": "Reverse Hierarchy",
          "display": "RèƲèřƨè Hïèřářçλ¥",
          "desc": "Tλè RèƲèřƨè Hïèřářçλ¥ ƭôϱϱℓè çáúƨèƨ λïèřářçλ¥ ƭô βè ï₥ƥôƨèδ ƒřô₥ ƭλè βôƭƭô₥ úƥ Ʋèřƨúƨ ƭλè ñôř₥áℓ ƭôƥ δôωñ."
        },
        {
          "name": "Pass Null Through Surfaces",
          "display": "Þáƨƨ Núℓℓ Tλřôúϱλ §úřƒáçèƨ",
          "desc": "Tλè Þáƨƨ Núℓℓ Tλřôúϱλ §úřƒáçèƨ ƭôϱϱℓè çáúƨèƨ ƭλè Núℓℓ ñôδèƨ/çèℓℓƨ δèƒïñèδ ïñ áñ¥ ƨúřƒáçè ƭô βè ƥáƨƨèδ ƭô áℓℓ ôƒ ƭλè ƨúřƒáçèƨ."
        },
        {
          "name": "Surface Selection",
          "display": "§úřƒáçè §èℓèçƭïôñ",
          "desc": "Tλè §úřƒáçèƨ §èℓèçƭïôñ çôñƭřôℓƨ áℓℓôω ƭλè úƨèř ƭô ƨèℓèçƭ ωλïçλ ƨúřƒáçèƨ ářè ôúƭƥúƭ ƒôř Ʋïƨúáℓïƺáƭïôñ ôř ƨúβƨè9úèñƭ ƥřôçèƨƨïñϱ."
        }
      ]
    },
    {
      "name": "Data Settings",
      "display": "Ðáƭá §èƭƭïñϱƨ",
      "properties": [
        {
          "name": "Nodal Data To Map",
          "display": "Nôδáℓ Ðáƭá Tô Máƥ",
          "desc": "Tλè Nôδáℓ Ðáƭá Tô Máƥ ƭôϱϱℓèƨ áℓℓôω ¥ôú ƭô çôñƭřôℓ ωλïçλ δáƭá çô₥ƥôñèñƭƨ ářè ïñçℓúδèδ ïñ ƭλè ƨúřƒáçèƨ."
        },
        {
          "name": "Data Mapping",
          "display": "Ðáƭá Máƥƥïñϱ",
          "desc": "Tλè Ðáƭá Máƥƥïñϱ çôñƭřôℓ áℓℓôω ƭλè úƨèř ƭô ƨèℓèçƭ ƭô ωλïçλ ƨúřƒáçèƨ ƭλè ñôδáℓ δáƭá çô₥ƥôñèñƭƨ ářè ₥áƥƥèδ. Fôř èжá₥ƥℓè, ïƒ Tôƥ ïƨ ƨèℓèçƭèδ, ℓá¥èř ƭλïçƙñèƨƨèƨ ářè ₥áƥƥèδ ƭô ƭλè ƨúřƒáçè ƭλáƭ çôřřèƨƥôñδƨ ƭô ƭλè ƭôƥ ôƒ èáçλ ℓá¥èř."
        },
        {
          "name": "Set Min Max",
          "display": "§èƭ Mïñ Máж",
          "desc": "Tλè §èƭ Mïñ Máж çôñƭřôℓ áℓℓôωƨ ƭλè úƨèř ƭô èïƭλèř úƨè ƭλè ₥ïñ áñδ ₥áж ôƒ áℓℓ ƨúřƒáçèƨ, ôř ƭô ƨèƭ ƭλè ₥ïñ áñδ ₥áж ƭô ƭλáƭ ôƒ ƭλè ƨèℓèçƭèδ ƨúřƒáçèƨ."
        },
        {
          "name": "Cell Data To Map",
          "display": "Çèℓℓ Ðáƭá Tô Máƥ",
          "desc": "Tλè Çèℓℓ Ðáƭá Tô Máƥ ƭôϱϱℓèƨ áℓℓôω ¥ôú ƭô çôñƭřôℓ ωλïçλ çèℓℓ δáƭá çô₥ƥôñèñƭƨ ářè ïñçℓúδèδ ïñ ƭλè ƨúřƒáçèƨ."
        }
      ]
    },
    {
      "name": "Properties",
      "display": "Þřôƥèřƭïèƨ",
      "properties": [
        {
          "name": "Switch Property View",
          "display": "§ωïƭçλ Þřôƥèřƭ¥ Vïèω",
          "desc": "Éδïƭ ƭλè řèñδèřáβℓè (řèδ) ƥôřƭ ƥřôƥèřƭïèƨ ƒôř ƭλè ₥ôδúℓè."
        }
      ]
    }
  ]
}