{
  "name": "layer from surface",
  "display": "ℓá¥èř ƒřô₥ ƨúřƒáçè",
  "desc": "Tλè ℓá¥èř_ƒřô₥_ƨúřƒáçè ₥ôδúℓè çřèáƭèƨ á ℓá¥èř βáƨèδ ôñ áñ ïñƥúƭ ƨúřƒáçè áñδ Ʋářïáβℓè èℓèƲáƭïôñ Ʋáℓúè.",
  "categories": [
    {
      "name": "Properties",
      "display": "Þřôƥèřƭïèƨ",
      "properties": [
        {
          "name": "Surface Definition",
          "display": "§úřƒáçè Ðèƒïñïƭïôñ",
          "desc": "Tλè §úřƒáçè Ðèƒïñïƭïôñ ωïℓℓ áℓℓôω ƭλè úƨèř ƭô ƨèℓèçƭ ωλèƭλèř ƭλè §èℓèçƭèδ §úřƒáçè δèƒïñèƨ ƭλè ƭôƥ ôř ƭλè βôƭƭô₥ ôƒ ƭλè ℓá¥èř."
        },
        {
          "name": "Constant Value",
          "display": "Çôñƨƭáñƭ Váℓúè",
          "desc": "Tλè §èℓèçƭèδ §úřƒáçè ₥áƙèƨ úƥ ôñè ƨúřƒáçè ƒôř ƭλè ℓá¥èř, ƭλè Çôñƨƭáñƭ Váℓúè ïƨ ƭλè èℓèƲáƭïôñ ôƒ ƭλè ôƭλèř ƨúřƒáçè."
        },
        {
          "name": "Material Name",
          "display": "Máƭèřïáℓ Ná₥è",
          "desc": "Tλè Máƭèřïáℓ Ná₥è ƒôř ƭλè ñèωℓ¥ çřèáƭèδ ℓá¥èř."
        },
        {
          "name": "Material Number",
          "display": "Máƭèřïáℓ Nú₥βèř",
          "desc": "Tλè Máƭèřïáℓ Nú₥βèř ƒôř ƭλè ñèωℓ¥ çřèáƭèδ ℓá¥èř."
        },
        {
          "name": "Selected Surface",
          "display": "§èℓèçƭèδ §úřƒáçè",
          "desc": "Tλè §èℓèçƭèδ §úřƒáçè ƒřô₥ ƭλè Ìñƥúƭ Fïèℓδ úƨèδ ƭô çřèáƭè èïƭλèř ƭλè ƭôƥ ôř βôƭƭô₥ ôƒ ƭλè ℓá¥èř."
        }
      ]
    }
  ]
}