{
  "name": "read_vtk",
  "display": "řèáδ_Ʋƭƙ",
  "desc": "Tλè řèáδ_VTK ₥ôδúℓè řèáδƨ á δáƭáƨèƭ ƒřô₥ ƭλè VTK ƒôř₥áƭ.",
  "categories": [
    {
      "name": "Properties",
      "display": "Þřôƥèřƭïèƨ",
      "properties": [
        {
          "name": "Units",
          "display": "Ûñïƭƨ",
          "desc": "Tλè çôôřδïñáƭè úñïƭƨ."
        }
      ]
    },
    {
      "name": "Properties",
      "display": "Þřôƥèřƭïèƨ",
      "properties": [
        {
          "name": "Switch Property View",
          "display": "§ωïƭçλ Þřôƥèřƭ¥ Vïèω",
          "desc": "Éδïƭ ƭλè řèñδèřáβℓè (řèδ) ƥôřƭ ƥřôƥèřƭïèƨ ƒôř ƭλè ₥ôδúℓè."
        },
        {
          "name": "Units",
          "display": "Ûñïƭƨ",
          "desc": "Tλè çôôřδïñáƭè úñïƭƨ."
        }
      ]
    }
  ]
}