{
  "name": "titles",
  "display": "ƭïƭℓèƨ",
  "desc": "Tλè ƭïƭℓèƨ ₥ôδúℓè ƥřôƲïδèƨ á ƨƭřáïϱλƭƒôřωářδ ₥èáñƨ ƭô ƥℓáçè ƭèжƭ ïñ ƭλè Vïèωèř.",
  "categories": [
    {
      "name": "Properties",
      "display": "Þřôƥèřƭïèƨ",
      "properties": [
        {
          "name": "Title Type",
          "display": "Tïƭℓè T¥ƥè",
          "desc": "Tλè Tïƭℓè T¥ƥè áℓℓôωƨ ƭλè úƨèř ƭô çλôôƨè βèƭωèèñ á 2Ð ƭïƭℓè ïñ ƭλè ôƲèřℓá¥, ôř á 3Ð ƭïƭℓè ƭλáƭ ïƨ ïñ ƭλè ₥ôδèℓ ƨƥáçè."
        },
        {
          "name": "X Coordinate",
          "display": "X Çôôřδïñáƭè",
          "desc": "Tλè X Çôôřδïñáƭè ƨƥèçïƒïèƨ ƭλè ℓôçáƭïôñ ôƒ ƭλè ℓôωèř ℓèƒƭ èδϱè ôƒ ƭλè ƭïƭℓè ïñ 2Ð ôƲèřℓá¥ ƨƥáçè (ï.è. ƒřô₥ -1.0 ƭô 1.0)."
        },
        {
          "name": "Y Coordinate",
          "display": "Ý Çôôřδïñáƭè",
          "desc": "Tλè Ý Çôôřδïñáƭè ƨƥèçïƒïèƨ ƭλè ℓôçáƭïôñ ôƒ ƭλè ℓôωèř ℓèƒƭ èδϱè ôƒ ƭλè ƭïƭℓè ïñ 2Ð ôƲèřℓá¥ ƨƥáçè (ï.è. ƒřô₥ -1.0 ƭô 1.0)."
        },
        {
          "name": "Z Coordinate",
          "display": "Z Çôôřδïñáƭè",
          "desc": "Tλè Z Çôôřδïñáƭè ƨƥèçïƒïèƨ ƭλè ℓôçáƭïôñ ôƒ ƭλè ℓôωèř ℓèƒƭ èδϱè ôƒ ƭλè ƭïƭℓè ïñ 2Ð ôƲèřℓá¥ ƨƥáçè (ï.è. ƒřô₥ -1.0 ƭô 1.0)."
        },
        {
          "name": "X Coordinate 3D",
          "display": "X Çôôřδïñáƭè 3Ð",
          "desc": "Tλè X Çôôřδïñáƭè ƨƥèçïƒïèƨ ƭλè ℓôçáƭïôñ ôƒ ƭλè ℓôωèř ℓèƒƭ èδϱè ôƒ ƭλè ƭïƭℓè ïñ çôôřδïñáƭè ƨƥáçè."
        },
        {
          "name": "Y Coordinate 3D",
          "display": "Ý Çôôřδïñáƭè 3Ð",
          "desc": "Tλè Ý Çôôřδïñáƭè ƨƥèçïƒïèƨ ƭλè ℓôçáƭïôñ ôƒ ƭλè ℓôωèř ℓèƒƭ èδϱè ôƒ ƭλè ƭïƭℓè ïñ çôôřδïñáƭè ƨƥáçè."
        },
        {
          "name": "Z Coordinate 3D",
          "display": "Z Çôôřδïñáƭè 3Ð",
          "desc": "Tλè Z Çôôřδïñáƭè ƨƥèçïƒïèƨ ƭλè ℓôçáƭïôñ ôƒ ƭλè ℓôωèř ℓèƒƭ èδϱè ôƒ ƭλè ƭïƭℓè ïñ çôôřδïñáƭè ƨƥáçè."
        },
        {
          "name": "Width Height Ratio",
          "display": "Wïδƭλ Hèïϱλƭ Ráƭïô",
          "desc": "Tλè Wïδƭλ Hèïϱλƭ Ráƭïô áℓℓôωƨ ¥ôú ƭô ƨƭřèƭçλ ôř çô₥ƥřèƨƨ ƭλè ƒôñƭ ƭô áδJúƨƭ ƒôř ñôñ-ƨ9úářè Vïèωèř ïñδúçèδ δïƨƭôřƭïôñƨ."
        },
        {
          "name": "Title Text",
          "display": "Tïƭℓè Tèжƭ",
          "desc": "Tλè Tïℓè Tèжƭ ïƨ ƭλè ƭèжƭ ƭô úƨè ƒôř ƭλè Tïƭℓè."
        },
        {
          "name": "Title Color",
          "display": "Tïƭℓè Çôℓôř",
          "desc": ""
        },
        {
          "name": "Font Type",
          "display": "Fôñƭ T¥ƥè",
          "desc": "Tλè £áβèℓ T¥ƥè áℓℓôωƨ ƭλè úƨèř ƭô ƨèℓèçƭ βèƭωèèñ ƭλřèè ƒôñƭ ƭ¥ƥèƨ. Fôřωářδ Fáçïñϱ Fôñƭƨ ωïℓℓ áℓωá¥ƨ βè áℓïϱñèδ ƭô ƭλè Vïèω.  TřúèT¥ƥè ƒôñƭƨ ářè ƨƭáñδářδ ƒôñƭƨ.  £ïñè ƒôñƭƨ ářè ℓôω ï₥ƥáçƭ ƒôñƭƨ ωλïçλ ƥèřƒôř₥ βèƭƭèř ωλèñ ℓářϱè ñú₥βèřƨ ôƒ ℓáβèℓƨ ářè ϱèñèřáƭèδ."
        },
        {
          "name": "Forward Facing Style",
          "display": "Fôřωářδ Fáçïñϱ §ƭ¥ℓè",
          "desc": "Fôřωářδ Fáçïñϱ §ƭ¥ℓè áℓℓôωƨ ƭλè úƨèř ƭô áℓïϱñ ƭλè ℓáβèℓƨ ƭô áñ áƥƥřôƥřïáƭè Ʋïèω áñδ ƭô áℓƭèř ƭλè βáƨïç ℓá¥ôúƭ ôƒ ƭλè ƒôñƭ."
        },
        {
          "name": "TrueType Font Style",
          "display": "TřúèT¥ƥè Fôñƭ §ƭ¥ℓè",
          "desc": "Tλè TřúèT¥ƥè Fôñƭ §ƭ¥ℓè áℓℓôωƨ ƭλè úƨèř ƭô áℓƭèř ƭλè βáƨïç ℓôôƙ ôƒ ƭλè ƒôñƭ."
        },
        {
          "name": "Line Font Style",
          "display": "£ïñè Fôñƭ §ƭ¥ℓè",
          "desc": "Tλè £ïñè Fôñƭ §ƭ¥ℓè áℓℓôωƨ ƭλè úƨèř ƭô áℓƭèř ƭλè βáƨïç ℓôôƙ ôƒ ƭλè ƒôñƭ."
        },
        {
          "name": "3D Font Settings",
          "display": "3Ð Fôñƭ §èƭƭïñϱƨ",
          "desc": "3Ð £áβèℓ §èƭƭïñϱƨ áℓℓôω ƭλè úƨèř ƭô áℓïϱñ ƭλè ℓáβèℓƨ ƭô áñ áƥƥřôƥřïáƭè Ʋïèω."
        }
      ]
    },
    {
      "name": "Properties",
      "display": "Þřôƥèřƭïèƨ",
      "properties": [
        {
          "name": "Switch Property View",
          "display": "§ωïƭçλ Þřôƥèřƭ¥ Vïèω",
          "desc": "Éδïƭ ƭλè řèñδèřáβℓè (řèδ) ƥôřƭ ƥřôƥèřƭïèƨ ƒôř ƭλè ₥ôδúℓè."
        },
        {
          "name": "Title Type",
          "display": "Tïƭℓè T¥ƥè",
          "desc": "Tλè Tïƭℓè T¥ƥè áℓℓôωƨ ƭλè úƨèř ƭô çλôôƨè βèƭωèèñ á 2Ð ƭïƭℓè ïñ ƭλè ôƲèřℓá¥, ôř á 3Ð ƭïƭℓè ƭλáƭ ïƨ ïñ ƭλè ₥ôδèℓ ƨƥáçè."
        },
        {
          "name": "X Coordinate",
          "display": "X Çôôřδïñáƭè",
          "desc": "Tλè X Çôôřδïñáƭè ƨƥèçïƒïèƨ ƭλè ℓôçáƭïôñ ôƒ ƭλè ℓôωèř ℓèƒƭ èδϱè ôƒ ƭλè ƭïƭℓè ïñ 2Ð ôƲèřℓá¥ ƨƥáçè (ï.è. ƒřô₥ -1.0 ƭô 1.0)."
        },
        {
          "name": "Y Coordinate",
          "display": "Ý Çôôřδïñáƭè",
          "desc": "Tλè Ý Çôôřδïñáƭè ƨƥèçïƒïèƨ ƭλè ℓôçáƭïôñ ôƒ ƭλè ℓôωèř ℓèƒƭ èδϱè ôƒ ƭλè ƭïƭℓè ïñ 2Ð ôƲèřℓá¥ ƨƥáçè (ï.è. ƒřô₥ -1.0 ƭô 1.0)."
        },
        {
          "name": "Z Coordinate",
          "display": "Z Çôôřδïñáƭè",
          "desc": "Tλè Z Çôôřδïñáƭè ƨƥèçïƒïèƨ ƭλè ℓôçáƭïôñ ôƒ ƭλè ℓôωèř ℓèƒƭ èδϱè ôƒ ƭλè ƭïƭℓè ïñ 2Ð ôƲèřℓá¥ ƨƥáçè (ï.è. ƒřô₥ -1.0 ƭô 1.0)."
        },
        {
          "name": "X Coordinate 3D",
          "display": "X Çôôřδïñáƭè 3Ð",
          "desc": "Tλè X Çôôřδïñáƭè ƨƥèçïƒïèƨ ƭλè ℓôçáƭïôñ ôƒ ƭλè ℓôωèř ℓèƒƭ èδϱè ôƒ ƭλè ƭïƭℓè ïñ çôôřδïñáƭè ƨƥáçè."
        },
        {
          "name": "Y Coordinate 3D",
          "display": "Ý Çôôřδïñáƭè 3Ð",
          "desc": "Tλè Ý Çôôřδïñáƭè ƨƥèçïƒïèƨ ƭλè ℓôçáƭïôñ ôƒ ƭλè ℓôωèř ℓèƒƭ èδϱè ôƒ ƭλè ƭïƭℓè ïñ çôôřδïñáƭè ƨƥáçè."
        },
        {
          "name": "Z Coordinate 3D",
          "display": "Z Çôôřδïñáƭè 3Ð",
          "desc": "Tλè Z Çôôřδïñáƭè ƨƥèçïƒïèƨ ƭλè ℓôçáƭïôñ ôƒ ƭλè ℓôωèř ℓèƒƭ èδϱè ôƒ ƭλè ƭïƭℓè ïñ çôôřδïñáƭè ƨƥáçè."
        },
        {
          "name": "Width Height Ratio",
          "display": "Wïδƭλ Hèïϱλƭ Ráƭïô",
          "desc": "Tλè Wïδƭλ Hèïϱλƭ Ráƭïô áℓℓôωƨ ¥ôú ƭô ƨƭřèƭçλ ôř çô₥ƥřèƨƨ ƭλè ƒôñƭ ƭô áδJúƨƭ ƒôř ñôñ-ƨ9úářè Vïèωèř ïñδúçèδ δïƨƭôřƭïôñƨ."
        },
        {
          "name": "Title Text",
          "display": "Tïƭℓè Tèжƭ",
          "desc": "Tλè Tïℓè Tèжƭ ïƨ ƭλè ƭèжƭ ƭô úƨè ƒôř ƭλè Tïƭℓè."
        },
        {
          "name": "Title Color",
          "display": "Tïƭℓè Çôℓôř",
          "desc": ""
        },
        {
          "name": "Font Type",
          "display": "Fôñƭ T¥ƥè",
          "desc": "Tλè £áβèℓ T¥ƥè áℓℓôωƨ ƭλè úƨèř ƭô ƨèℓèçƭ βèƭωèèñ ƭλřèè ƒôñƭ ƭ¥ƥèƨ. Fôřωářδ Fáçïñϱ Fôñƭƨ ωïℓℓ áℓωá¥ƨ βè áℓïϱñèδ ƭô ƭλè Vïèω.  TřúèT¥ƥè ƒôñƭƨ ářè ƨƭáñδářδ ƒôñƭƨ.  £ïñè ƒôñƭƨ ářè ℓôω ï₥ƥáçƭ ƒôñƭƨ ωλïçλ ƥèřƒôř₥ βèƭƭèř ωλèñ ℓářϱè ñú₥βèřƨ ôƒ ℓáβèℓƨ ářè ϱèñèřáƭèδ."
        },
        {
          "name": "Forward Facing Style",
          "display": "Fôřωářδ Fáçïñϱ §ƭ¥ℓè",
          "desc": "Fôřωářδ Fáçïñϱ §ƭ¥ℓè áℓℓôωƨ ƭλè úƨèř ƭô áℓïϱñ ƭλè ℓáβèℓƨ ƭô áñ áƥƥřôƥřïáƭè Ʋïèω áñδ ƭô áℓƭèř ƭλè βáƨïç ℓá¥ôúƭ ôƒ ƭλè ƒôñƭ."
        },
        {
          "name": "TrueType Font Style",
          "display": "TřúèT¥ƥè Fôñƭ §ƭ¥ℓè",
          "desc": "Tλè TřúèT¥ƥè Fôñƭ §ƭ¥ℓè áℓℓôωƨ ƭλè úƨèř ƭô áℓƭèř ƭλè βáƨïç ℓôôƙ ôƒ ƭλè ƒôñƭ."
        },
        {
          "name": "Line Font Style",
          "display": "£ïñè Fôñƭ §ƭ¥ℓè",
          "desc": "Tλè £ïñè Fôñƭ §ƭ¥ℓè áℓℓôωƨ ƭλè úƨèř ƭô áℓƭèř ƭλè βáƨïç ℓôôƙ ôƒ ƭλè ƒôñƭ."
        },
        {
          "name": "3D Font Settings",
          "display": "3Ð Fôñƭ §èƭƭïñϱƨ",
          "desc": "3Ð £áβèℓ §èƭƭïñϱƨ áℓℓôω ƭλè úƨèř ƭô áℓïϱñ ƭλè ℓáβèℓƨ ƭô áñ áƥƥřôƥřïáƭè Ʋïèω."
        }
      ]
    }
  ]
}