{
  "name": "add logo",
  "display": "add logo",
  "desc": "该模块用来放置一个logo或者其他图形对象到查看器。",
  "categories": [
    {
      "name": "Properties",
      "display": "属性",
      "properties": [
        {
          "name": "Logo Image File",
          "display": "Logo 图片文件",
          "desc": "logo的图片路径。"
        }
      ]
    },
    {
      "name": "Display Settings",
      "display": "显示设置",
      "properties": [
        {
          "name": "Logo Size",
          "display": "Logo 尺寸",
          "desc": "Logo尺寸将改变重叠空间中图像的宽度和高度。"
        },
        {
          "name": "Horizontal Translation",
          "display": "水平平移",
          "desc": "水平平移将标志在叠加空间的水平方向上移动。"
        },
        {
          "name": "Vertical Translation",
          "display": "竖直平移",
          "desc": "竖直平移将标志在叠加空间的水平方向上移动。"
        },
        {
          "name": "Overlay",
          "display": "覆盖",
          "desc": "覆盖控件允许用户将Logo放在模型的后面或前面。"
        },
        {
          "name": "Mask Image",
          "display": "遮罩图片",
          "desc": "图片遮罩将把与遮罩颜色相同的所有像素的不透明度设置为零。"
        },
        {
          "name": "Mask Color",
          "display": "遮罩颜色",
          "desc": "当打开遮罩图片后，遮罩颜色用来选择被遮罩的像素。"
        }
      ]
    }
  ]
}